TILatex/TILatex.py
TILatex/__init__.py
tilatex-2.0.0.dist-info/METADATA
tilatex-2.0.0.dist-info/WHEEL
tilatex-2.0.0.dist-info/top_level.txt
tilatex-2.0.0.dist-info/RECORD
